fallbeyging/__init__.py
fallbeyging/__main__.py
fallbeyging/fallbeyging.py
fallbeyging/game.py
fallbeyging/assets/__init__.py
fallbeyging/assets/processed/bin_words_no_capital_inflection.json
fallbeyging/bin_data/bin_create.py
fallbeyging/bin_data/bin_load.py
fallbeyging/objects/__init.py
fallbeyging/objects/button.py
fallbeyging/objects/fall_box.py
fallbeyging/objects/input_box.py
fallbeyging/objects/text_box.py
fallbeyging-1.3.data/data/assets/bin_words_no_capital_inflection.json
fallbeyging-1.3.data/scripts/fallbeyging
fallbeyging-1.3.dist-info/METADATA
fallbeyging-1.3.dist-info/WHEEL
fallbeyging-1.3.dist-info/top_level.txt
fallbeyging-1.3.dist-info/RECORD
