Metadata-Version: 2.1
Name: fallbeyging
Version: 1.3
Summary: UNKNOWN
Home-page: https://github.com/slowpokesheep/fallbeyging
Author: Slowpoke
Author-email: UNKNOWN
License: UNKNOWN
Platform: UNKNOWN
Requires-Dist: pygame
